LICENSE
README.md
timeitX/__init__.py
timeitx-1.0.2.dist-info/LICENSE
timeitx-1.0.2.dist-info/METADATA
timeitx-1.0.2.dist-info/WHEEL
timeitx-1.0.2.dist-info/RECORD
