Metadata-Version: 2.1
Name: timeitX
Version: 1.0.2
Summary: timeitX - Function Execution Time Logger
Keywords: timeit,async timeit,async,timer,python
Author: Nitish Sai Kommaraju
Requires-Python: >=3.9,<4.0
Classifier: Programming Language :: Python :: 3
Classifier: Programming Language :: Python :: 3.9
Classifier: Programming Language :: Python :: 3.10
Classifier: Programming Language :: Python :: 3.11
Classifier: Programming Language :: Python :: 3.12
